azure/mgmt/iotoperations/__init__.py
azure/mgmt/iotoperations/_client.py
azure/mgmt/iotoperations/_configuration.py
azure/mgmt/iotoperations/_model_base.py
azure/mgmt/iotoperations/_patch.py
azure/mgmt/iotoperations/_serialization.py
azure/mgmt/iotoperations/_version.py
azure/mgmt/iotoperations/py.typed
azure/mgmt/iotoperations/aio/__init__.py
azure/mgmt/iotoperations/aio/_client.py
azure/mgmt/iotoperations/aio/_configuration.py
azure/mgmt/iotoperations/aio/_patch.py
azure/mgmt/iotoperations/aio/operations/__init__.py
azure/mgmt/iotoperations/aio/operations/_operations.py
azure/mgmt/iotoperations/aio/operations/_patch.py
azure/mgmt/iotoperations/models/__init__.py
azure/mgmt/iotoperations/models/_enums.py
azure/mgmt/iotoperations/models/_models.py
azure/mgmt/iotoperations/models/_patch.py
azure/mgmt/iotoperations/operations/__init__.py
azure/mgmt/iotoperations/operations/_operations.py
azure/mgmt/iotoperations/operations/_patch.py
azure_mgmt_iotoperations-1.0.0.dist-info/LICENSE
azure_mgmt_iotoperations-1.0.0.dist-info/METADATA
azure_mgmt_iotoperations-1.0.0.dist-info/WHEEL
azure_mgmt_iotoperations-1.0.0.dist-info/top_level.txt
azure_mgmt_iotoperations-1.0.0.dist-info/RECORD
